MANIFEST.in
README.rst
setup.py
src/AUTHORS.txt
src/HISTORY.txt
src/README.txt
src/sphinxjp/__init__.py
src/sphinxjp.themes.tinkerbelizeholesidebar.egg-info/PKG-INFO
src/sphinxjp.themes.tinkerbelizeholesidebar.egg-info/SOURCES.txt
src/sphinxjp.themes.tinkerbelizeholesidebar.egg-info/dependency_links.txt
src/sphinxjp.themes.tinkerbelizeholesidebar.egg-info/entry_points.txt
src/sphinxjp.themes.tinkerbelizeholesidebar.egg-info/namespace_packages.txt
src/sphinxjp.themes.tinkerbelizeholesidebar.egg-info/not-zip-safe
src/sphinxjp.themes.tinkerbelizeholesidebar.egg-info/requires.txt
src/sphinxjp.themes.tinkerbelizeholesidebar.egg-info/top_level.txt
src/sphinxjp/themes/__init__.py
src/sphinxjp/themes/tinkerbelizeholesidebar/__init__.py
src/sphinxjp/themes/tinkerbelizeholesidebar/templates/tinkerbelizeholesidebar/layout.html
src/sphinxjp/themes/tinkerbelizeholesidebar/templates/tinkerbelizeholesidebar/theme.conf
src/sphinxjp/themes/tinkerbelizeholesidebar/templates/tinkerbelizeholesidebar/static/pygments.css
src/sphinxjp/themes/tinkerbelizeholesidebar/templates/tinkerbelizeholesidebar/static/tinkerbelizeholesidebar.css_t